fqa_web_app/__init__.py
fqa_web_app/feedback_system_abc.py
fqa_web_app/gui.py
fqa_web_app/samples.py
fqa_web_app/toy_models.py
fqa_web_app/utils.py
fqa_web_app-0.1.0rc8.dist-info/METADATA
fqa_web_app-0.1.0rc8.dist-info/WHEEL
fqa_web_app-0.1.0rc8.dist-info/top_level.txt
fqa_web_app-0.1.0rc8.dist-info/RECORD
