Metadata-Version: 2.1
Name: fqa-web-app
Version: 0.1.0rc8
Summary: The web app and UI for FeedbackQA.
Home-page: UNKNOWN
Author: Xing Han Lu
Author-email: github@xinghanlu.com
License: UNKNOWN
Platform: UNKNOWN
Classifier: Programming Language :: Python :: 3.6
Classifier: Programming Language :: Python :: 3.7
Classifier: Programming Language :: Python :: 3.8
Classifier: License :: OSI Approved :: MIT License
Classifier: Operating System :: OS Independent
Requires-Python: >=3.6
Requires-Dist: jupyter-dash (>=0.3.0)
Requires-Dist: dash (>=1.11.0)
Requires-Dist: gunicorn
Requires-Dist: tomd
Requires-Dist: lxml
Requires-Dist: beautifulsoup4
Requires-Dist: dash-bootstrap-components
Requires-Dist: pyngrok
